MANIFEST.in
README.txt
setup.py
docs/HISTORY.txt
src/zeam/__init__.py
src/zeam.form.autofields.egg-info/PKG-INFO
src/zeam.form.autofields.egg-info/SOURCES.txt
src/zeam.form.autofields.egg-info/dependency_links.txt
src/zeam.form.autofields.egg-info/namespace_packages.txt
src/zeam.form.autofields.egg-info/not-zip-safe
src/zeam.form.autofields.egg-info/requires.txt
src/zeam.form.autofields.egg-info/top_level.txt
src/zeam/form/__init__.py
src/zeam/form/autofields/__init__.py
src/zeam/form/autofields/configure.zcml
src/zeam/form/autofields/datamanager.py
src/zeam/form/autofields/fields.py
src/zeam/form/autofields/ftesting.zcml
src/zeam/form/autofields/interfaces.py
src/zeam/form/autofields/meta.py
src/zeam/form/autofields/testing.py
src/zeam/form/autofields/tests/__init__.py
src/zeam/form/autofields/tests/fields.txt
src/zeam/form/autofields/tests/test_doctest.py