Metadata-Version: 1.0
Name: zeam.form.autofields
Version: 1.0.1
Summary: Automatically collect fields for a Zeam Form.
Home-page: http://pypi.python.org/pypi/zeam.form.autofields
Author: Sylvain Viollon
Author-email: thefunny@gmail.com
License: BSD
Keywords: zeam form fields collect
Platform: UNKNOWN
Classifier: Framework :: Zope3
Classifier: Programming Language :: Python
Classifier: Programming Language :: Zope
Classifier: Intended Audience :: Developers
Classifier: Topic :: Software Development :: Libraries :: Python Modules
